ssort/__init__.py
ssort/__main__.py
ssort/_ast.py
ssort/_bindings.py
ssort/_builtins.py
ssort/_dependencies.py
ssort/_exceptions.py
ssort/_files.py
ssort/_graphs.py
ssort/_main.py
ssort/_method_requirements.py
ssort/_overloads.py
ssort/_parsing.py
ssort/_requirements.py
ssort/_ssort.py
ssort/_statements.py
ssort/_utils.py
ssort/_version.py
ssort-0.16.0.dist-info/licenses/LICENSE
ssort-0.16.0.dist-info/METADATA
ssort-0.16.0.dist-info/WHEEL
ssort-0.16.0.dist-info/entry_points.txt
ssort-0.16.0.dist-info/top_level.txt
ssort-0.16.0.dist-info/RECORD
