Metadata-Version: 2.4
Name: ssort
Version: 0.16.0
Summary: The python statement sorter
Author-email: Ben Mather <bwhmather@bwhmather.com>
Maintainer-email: Ben Mather <bwhmather@bwhmather.com>
License: MIT
Project-URL: Homepage, https://github.com/bwhmather/ssort
Classifier: Development Status :: 5 - Production/Stable
Classifier: Environment :: Console
Classifier: Intended Audience :: Developers
Classifier: License :: OSI Approved :: MIT License
Classifier: Programming Language :: Python :: 3
Classifier: Programming Language :: Python :: 3.9
Classifier: Programming Language :: Python :: 3.10
Classifier: Programming Language :: Python :: 3.11
Classifier: Programming Language :: Python :: 3.12
Classifier: Programming Language :: Python :: 3.13
Classifier: Programming Language :: Python :: 3.14
Classifier: Programming Language :: Python
Classifier: Topic :: Software Development :: Libraries :: Python Modules
Classifier: Topic :: Software Development :: Quality Assurance
Requires-Python: >=3.9
License-File: LICENSE
Requires-Dist: pathspec>=0.9.0
Dynamic: license-file
